README.md
setup.cfg
setup.py
cectf_proxy/__init__.py
cectf_proxy/celery.py
cectf_proxy/database.py
cectf_proxy/routes.py
cectf_proxy/stats.py
cectf_proxy.egg-info/PKG-INFO
cectf_proxy.egg-info/SOURCES.txt
cectf_proxy.egg-info/dependency_links.txt
cectf_proxy.egg-info/not-zip-safe
cectf_proxy.egg-info/requires.txt
cectf_proxy.egg-info/top_level.txt